live_audio_capture/__init__.py
live_audio_capture/audio_capture.py
live_audio_capture/audio_noise_reduction.py
live_audio_capture/vad.py
live_audio_capture/visualization.py
live_audio_capture/audio_utils/__init__.py
live_audio_capture/audio_utils/audio_playback.py
live_audio_capture/audio_utils/audio_processing.py
live_audio_capture/audio_utils/mic_utils.py
tests/__init__.py
tests/test_audio_capture.py
tests/test_vad.py
live_audio_capture-0.4.1.dist-info/LICENSE
live_audio_capture-0.4.1.dist-info/METADATA
live_audio_capture-0.4.1.dist-info/WHEEL
live_audio_capture-0.4.1.dist-info/top_level.txt
live_audio_capture-0.4.1.dist-info/RECORD
