Metadata-Version: 2.1
Name: live-audio-capture
Version: 0.4.1
Summary: A cross-platform utility for capturing live audio from a microphone using FFmpeg.
Home-page: https://github.com/sami-rajichi/live_audio_capture
Author: Sami RAJICHI
Author-email: semi.rajichi@gmail.com
License: MIT
Project-URL: Bug Reports, https://github.com/sami-rajichi/live_audio_capture/issues
Project-URL: Source, https://github.com/sami-rajichi/live_audio_capture
Project-URL: Homepage, https://sami-rajichi.github.io/live_audio_capture/
Keywords: audio capture ffmpeg real-time visualization
Classifier: Development Status :: 4 - Beta
Classifier: Intended Audience :: Developers
Classifier: Intended Audience :: Science/Research
Classifier: License :: OSI Approved :: MIT License
Classifier: Programming Language :: Python :: 3
Classifier: Programming Language :: Python :: 3.9
Classifier: Programming Language :: Python :: 3.10
Classifier: Programming Language :: Python :: 3.11
Classifier: Programming Language :: Python :: 3.12
Classifier: Programming Language :: Python :: 3.13
Classifier: Operating System :: OS Independent
Classifier: Topic :: Multimedia :: Sound/Audio
Classifier: Topic :: Software Development :: Libraries :: Python Modules
Requires-Python: >=3.9
License-File: LICENSE
Requires-Dist: numpy >=1.26.4
Requires-Dist: scipy >=1.12.0
Requires-Dist: pydub >=0.25.1
Requires-Dist: pyqtgraph >=0.13.7
Requires-Dist: noisereduce >=3.0.3
Requires-Dist: sounddevice >=0.4.6
Requires-Dist: simpleaudio >=1.0.4
Provides-Extra: dev
Requires-Dist: pytest >=8.3.4 ; extra == 'dev'
Requires-Dist: flake8 >=7.1.1 ; extra == 'dev'
Requires-Dist: twine >=6.0.1 ; extra == 'dev'
Provides-Extra: torch
Requires-Dist: torch >=2.2.1 ; extra == 'torch'
